galilei/__init__.py
galilei/backends/GPy.py
galilei/backends/__init__.py
galilei/backends/jax.py
galilei/backends/sklearn.py
galilei/backends/torch.py
galilei/cli.py
galilei/emulator.py
galilei/experimental.py
galilei/sampling.py
galilei-0.3.1.dist-info/METADATA
galilei-0.3.1.dist-info/WHEEL
galilei-0.3.1.dist-info/entry_points.txt
galilei-0.3.1.dist-info/LICENSE
galilei-0.3.1.dist-info/RECORD
